mclimate/__init__.py
mclimate/async_wrapper.py
mclimate/core.py
mclimate/exceptions.py
mclimate/wrapper.py
py_mclimate_api-1.0.2.dist-info/LICENSE
py_mclimate_api-1.0.2.dist-info/METADATA
py_mclimate_api-1.0.2.dist-info/WHEEL
py_mclimate_api-1.0.2.dist-info/top_level.txt
py_mclimate_api-1.0.2.dist-info/RECORD
