Metadata-Version: 2.1
Name: py-mclimate-api
Version: 1.0.2
Summary: MClimate API Wrapper in Python
Home-page: https://github.com/Pernichev/mclimate_api_wrapper
Author: MClimate
Author-email: hi@seemelissa.com
License: UNKNOWN
Platform: UNKNOWN
Classifier: Programming Language :: Python :: 3
Classifier: License :: OSI Approved :: MIT License
Classifier: Operating System :: OS Independent
Requires-Python: >=3.6
